myre/__init__.py
myre/match.py
myre/pattern.py
myre/protocol.py
myre-0.0.8.dist-info/METADATA
myre-0.0.8.dist-info/WHEEL
myre-0.0.8.dist-info/licenses/LICENSE
myre-0.0.8.dist-info/RECORD
