Metadata-Version: 2.4
Name: myre
Version: 0.0.8
Summary: Human Readable Regular Expression
Author-email: blurhead <blurhead@outlook.com>
License: MIT
License-File: LICENSE
Requires-Python: >=3.10
Requires-Dist: typing-extensions>=4.9.0
Provides-Extra: dev
Requires-Dist: mypy>=1.0; extra == 'dev'
Requires-Dist: pre-commit>=3.0; extra == 'dev'
Requires-Dist: pytest>=8.0; extra == 'dev'
Requires-Dist: ruff>=0.1.0; extra == 'dev'
